{ "_t" : "BH.oM.Data.Library.Dataset", "BHoM_Guid" : "ad94794f-e045-46a6-bf78-dd3a4f85e6b3", "Name" : "FromTonnePerCubicMillimetre", "Fragments" : [], "Tags" : [], "CustomData" : { }, "SourceInformation" : { "_t" : "BH.oM.Data.Library.Source", "BHoM_Guid" : "a80650a9-76c6-439d-aebc-c45daaf5228d", "Name" : "", "Fragments" : [], "Tags" : [], "CustomData" : { }, "SourceLink" : "", "Title" : "", "Author" : "Roly Hudson", "ItemReference" : "", "Version" : "", "Publisher" : "", "Schema" : "", "Language" : "", "Location" : "", "Copyright" : "", "Contributors" : "" }, "TimeOfCreation" : { "$date" : 1607592696347 }, "Data" : [{ "_t" : "BH.oM.Test.UnitTests.UnitTest", "BHoM_Guid" : "26141301-a3e7-4fd9-b742-ead4897df9bf", "Name" : "", "Fragments" : [], "Tags" : [], "CustomData" : { }, "Method" : { "_t" : "System.Reflection.MethodBase", "TypeName" : "{ \"_t\" : \"System.Type\", \"Name\" : \"BH.Engine.Units.Convert, Units_Engine, Version=4.0.0.0, Culture=neutral, PublicKeyToken=null\" }", "MethodName" : "FromTonnePerCubicMillimetre", "Parameters" : ["{ \"_t\" : \"System.Type\", \"Name\" : \"System.Double, mscorlib, Version=4.0.0.0, Culture=neutral, PublicKeyToken=b77a5c561934e089\" }"] }, "Data" : [{ "_t" : "BH.oM.Test.UnitTests.TestData", "BHoM_Guid" : "26880c61-4dc3-453d-a717-04ac8cb1626d", "Name" : "", "Fragments" : [], "Tags" : [], "CustomData" : { }, "Inputs" : [1.0], "Outputs" : [1000000000000.0] }] }] }