{ "_t" : "BH.oM.Data.Library.Dataset", "BHoM_Guid" : "0ea8cf9c-0150-44a8-8cde-388574658efc", "Name" : "ToInchToTheFourth", "Fragments" : [], "Tags" : [], "CustomData" : { }, "SourceInformation" : { "_t" : "BH.oM.Data.Library.Source", "BHoM_Guid" : "f3b5d4d5-522e-4f9c-9fd9-98fe492d5d87", "Name" : "", "Fragments" : [], "Tags" : [], "CustomData" : { }, "SourceLink" : "", "Title" : "", "Author" : "Roly Hudson", "ItemReference" : "", "Version" : "", "Publisher" : "", "Schema" : "", "Language" : "", "Location" : "", "Copyright" : "", "Contributors" : "", "Confidence" : "Undefined" }, "TimeOfCreation" : { "$date" : 1607607419818 }, "Data" : [{ "_t" : "BH.oM.Test.UnitTests.UnitTest", "BHoM_Guid" : "2f3b12af-5b78-443b-802b-a0e727fb288f", "Name" : "", "Fragments" : [], "Tags" : [], "CustomData" : { }, "Method" : { "_t" : "System.Reflection.MethodBase", "TypeName" : "{ \"_t\" : \"System.Type\", \"Name\" : \"BH.Engine.Units.Convert, Units_Engine, Version=5.0.0.0, Culture=neutral, PublicKeyToken=null\", \"_bhomVersion\" : \"5.3\" }", "MethodName" : "ToInchToTheFourth", "Parameters" : ["{ \"_t\" : \"System.Type\", \"Name\" : \"System.Double, mscorlib, Version=4.0.0.0, Culture=neutral, PublicKeyToken=b77a5c561934e089\", \"_bhomVersion\" : \"5.3\" }"], "_bhomVersion" : "5.3" }, "Data" : [{ "_t" : "BH.oM.Test.UnitTests.TestData", "BHoM_Guid" : "daf617b5-dd23-4636-aa0c-d5a7b675e947", "Name" : "", "Fragments" : [], "Tags" : [], "CustomData" : { }, "Inputs" : [1.0], "Outputs" : [2402509.6100288304] }] }], "_bhomVersion" : "5.3" }