{ "_t" : "BH.oM.Data.Library.Dataset", "BHoM_Guid" : "dc38d955-2d65-4ff6-a5f2-5a86dd3495c6", "Name" : "ToKilogramPerLitre", "Fragments" : [], "Tags" : [], "CustomData" : { }, "SourceInformation" : { "_t" : "BH.oM.Data.Library.Source", "BHoM_Guid" : "e804c9f6-af79-43ad-9340-7cd9093248ab", "Name" : "", "Fragments" : [], "Tags" : [], "CustomData" : { }, "SourceLink" : "", "Title" : "", "Author" : "RH", "ItemReference" : "", "Version" : "", "Publisher" : "", "Schema" : "", "Language" : "", "Location" : "", "Copyright" : "", "Contributors" : "" }, "TimeOfCreation" : { "$date" : 1607586883234 }, "Data" : [{ "_t" : "BH.oM.Test.UnitTests.UnitTest", "BHoM_Guid" : "57cd9280-7e2a-4525-9abc-8c131328a64c", "Name" : "", "Fragments" : [], "Tags" : [], "CustomData" : { }, "Method" : { "_t" : "System.Reflection.MethodBase", "TypeName" : "{ \"_t\" : \"System.Type\", \"Name\" : \"BH.Engine.Units.Convert, Units_Engine, Version=4.0.0.0, Culture=neutral, PublicKeyToken=null\" }", "MethodName" : "ToKilogramPerLitre", "Parameters" : ["{ \"_t\" : \"System.Type\", \"Name\" : \"System.Double, mscorlib, Version=4.0.0.0, Culture=neutral, PublicKeyToken=b77a5c561934e089\" }"] }, "Data" : [{ "_t" : "BH.oM.Test.UnitTests.TestData", "BHoM_Guid" : "1638957c-1062-45aa-89d6-6621a401b125", "Name" : "", "Fragments" : [], "Tags" : [], "CustomData" : { }, "Inputs" : [1.0], "Outputs" : [0.001] }] }] }